QRCI/QRCI.py
QRCI/RCI.py
QRCI/__init__.py
QRCI/ring_descriptors.py
QRCI/utils.py
qrci-0.1.5.dist-info/licenses/LICENSE
qrci-0.1.5.dist-info/METADATA
qrci-0.1.5.dist-info/WHEEL
qrci-0.1.5.dist-info/top_level.txt
qrci-0.1.5.dist-info/RECORD
