Metadata-Version: 2.4
Name: qrci
Version: 0.1.5
Summary: Quantitative Ring Complexity Index
Author: Jianmin Wang
License: MIT License
Project-URL: Repository, https://github.com/AspirinCode/QRCI
Requires-Python: >=3.8
License-File: LICENSE
Requires-Dist: rdkit
Requires-Dist: numpy
Dynamic: license-file
